PyQtExtendedScene/__init__.py
PyQtExtendedScene/scene.py
PyQtExtendedScene-1.0.14.dist-info/LICENSE
PyQtExtendedScene-1.0.14.dist-info/METADATA
PyQtExtendedScene-1.0.14.dist-info/WHEEL
PyQtExtendedScene-1.0.14.dist-info/top_level.txt
PyQtExtendedScene-1.0.14.dist-info/RECORD
