Metadata-Version: 2.1
Name: PyQtExtendedScene
Version: 1.0.14
Summary: Extended scene library
Home-page: https://github.com/EPC-MSU/PyQtExtendedScene
Author: EPC MSU
Author-email: mihalin@physlab.ru
License: MIT
Platform: UNKNOWN
Classifier: Programming Language :: Python :: 3
Classifier: License :: OSI Approved :: MIT License
Classifier: Operating System :: OS Independent
Requires-Python: >=3.6, <=3.8.10
Requires-Dist: PyQt5 (<=5.15.0,>=5.8.2)
